dotect/__init__.py
dotect/base.py
dotect/detector_factory.py
dotect/ml_classifier.py
dotect/rule_detector.py
dotect-0.1.1.dist-info/LICENSE
dotect-0.1.1.dist-info/METADATA
dotect-0.1.1.dist-info/WHEEL
dotect-0.1.1.dist-info/RECORD
