Metadata-Version: 2.3
Name: dotect
Version: 0.1.1
Summary: Document detection and classification for financial documents
Author: Fin Officer Team
Requires-Python: >=3.8,<4.0
Classifier: Programming Language :: Python :: 3
Classifier: Programming Language :: Python :: 3.8
Classifier: Programming Language :: Python :: 3.9
Classifier: Programming Language :: Python :: 3.10
Classifier: Programming Language :: Python :: 3.11
Classifier: Programming Language :: Python :: 3.12
Classifier: Programming Language :: Python :: 3.13
Requires-Dist: invutil (>=0.1.0,<0.2.0)
Requires-Dist: pydantic (>=2.0.0,<3.0.0)
Requires-Dist: scikit-learn (>=1.0.0,<2.0.0)
Requires-Dist: spacy (>=3.0.0,<4.0.0)
Requires-Dist: transformers (>=4.0.0,<5.0.0)
